pyutils/__init__.py
pyutils/ansi.py
pyutils/argparse_utils.py
pyutils/bootstrap.py
pyutils/config.py
pyutils/dataclass_utils.py
pyutils/decorator_utils.py
pyutils/dict_utils.py
pyutils/exceptions.py
pyutils/exec_utils.py
pyutils/function_utils.py
pyutils/geocode.py
pyutils/graph.py
pyutils/id_generator.py
pyutils/iter_utils.py
pyutils/list_utils.py
pyutils/logging_utils.py
pyutils/math_utils.py
pyutils/misc_utils.py
pyutils/remote_worker.py
pyutils/state_tracker.py
pyutils/stopwatch.py
pyutils/string_utils.py
pyutils/text_utils.py
pyutils/unittest_utils.py
pyutils/unscrambler.py
pyutils/zookeeper.py
pyutils/collectionz/__init__.py
pyutils/collectionz/bidict.py
pyutils/collectionz/bst.py
pyutils/collectionz/interval_tree.py
pyutils/collectionz/shared_dict.py
pyutils/collectionz/trie.py
pyutils/compress/__init__.py
pyutils/compress/letter_compress.py
pyutils/datetimes/__init__.py
pyutils/datetimes/constants.py
pyutils/datetimes/dateparse_utils.py
pyutils/datetimes/dateparse_utilsLexer.py
pyutils/datetimes/dateparse_utilsListener.py
pyutils/datetimes/dateparse_utilsParser.py
pyutils/datetimes/datetime_utils.py
pyutils/files/__init__.py
pyutils/files/directory_filter.py
pyutils/files/file_utils.py
pyutils/files/lockfile.py
pyutils/parallelize/__init__.py
pyutils/parallelize/deferred_operand.py
pyutils/parallelize/executors.py
pyutils/parallelize/parallelize.py
pyutils/parallelize/selectable_event.py
pyutils/parallelize/smart_future.py
pyutils/parallelize/thread_utils.py
pyutils/search/__init__.py
pyutils/search/logical_search.py
pyutils/security/__init__.py
pyutils/security/acl.py
pyutils/typez/__init__.py
pyutils/typez/centcount.py
pyutils/typez/histogram.py
pyutils/typez/money.py
pyutils/typez/persistent.py
pyutils/typez/rate.py
pyutils/typez/type_hints.py
pyutils/typez/type_utils.py
pyutils-0.0.14.dist-info/LICENSE
pyutils-0.0.14.dist-info/METADATA
pyutils-0.0.14.dist-info/NOTICE
pyutils-0.0.14.dist-info/WHEEL
pyutils-0.0.14.dist-info/top_level.txt
pyutils-0.0.14.dist-info/RECORD
