Metadata-Version: 2.1
Name: pyutils
Version: 0.0.14
Summary: Python Utilities
Author-email: Scott Gasch <scott.gasch@gmail.com>
License: 
Project-URL: Homepage, https://wannabe.guru.org/pydocs/pyutils/pyutils.html
Project-URL: Bug Tracker, https://github.com/scottgasch/pyutils/issues
Project-URL: Repository, https://github.com/scottgasch/pyutils
Project-URL: Documentation, https://wannabe.guru.org/pydocs/pyutils/pyutils.html
Project-URL: Changelog, https://github.com/scottgasch/pyutils/blob/main/release_notes.md
Classifier: Development Status :: 3 - Alpha
Classifier: Programming Language :: Python :: 3
Classifier: License :: OSI Approved :: Apache Software License
Classifier: Operating System :: OS Independent
Requires-Python: >=3.9
License-File: LICENSE
License-File: NOTICE
Requires-Dist: antlr4-python3-runtime ==4.12.0
Requires-Dist: bitstring
Requires-Dist: cloudpickle
Requires-Dist: holidays
Requires-Dist: kazoo
Requires-Dist: overrides
Requires-Dist: pytz
Requires-Dist: requests
Provides-Extra: dev
Requires-Dist: black ; extra == 'dev'
Requires-Dist: coverage ; extra == 'dev'
Requires-Dist: flake8 ; extra == 'dev'
Requires-Dist: pylint ; extra == 'dev'
Requires-Dist: sphinx ; extra == 'dev'
